swarm_squad/__init__.py
swarm_squad/app.py
swarm_squad/core.py
swarm_squad/assets/__init__.py
swarm_squad/assets/favicon.ico
swarm_squad/assets/favicon.png
swarm_squad/assets/css/__init__.py
swarm_squad/assets/css/app.css
swarm_squad/assets/css/data.css
swarm_squad/assets/css/footer.css
swarm_squad/assets/css/home.css
swarm_squad/assets/css/nav.css
swarm_squad/assets/css/scrollbar.css
swarm_squad/assets/css/style.css
swarm_squad/assets/css/transition.css
swarm_squad/assets/js/__init__.py
swarm_squad/assets/js/boids.js
swarm_squad/assets/models/__init__.py
swarm_squad/assets/models/car.glb
swarm_squad/assets/models/drone.glb
swarm_squad/assets/screenshots/data.png
swarm_squad/assets/screenshots/home.png
swarm_squad/assets/screenshots/map.png
swarm_squad/assets/screenshots/nav.png
swarm_squad/cli/__init__.py
swarm_squad/cli/command.py
swarm_squad/cli/list.py
swarm_squad/cli/run.py
swarm_squad/cli/webui.py
swarm_squad/components/__init__.py
swarm_squad/components/chat_component.py
swarm_squad/components/map_component.html
swarm_squad/components/plot_component.py
swarm_squad/components/table_component.py
swarm_squad/data/README.md
swarm_squad/data/__init__.py
swarm_squad/data/agent_fake_data.py
swarm_squad/data/mission_fake_data.py
swarm_squad/data/system_fake_data.py
swarm_squad/data/telemetry_fake_data.py
swarm_squad/pages/__init__.py
swarm_squad/pages/chat.py
swarm_squad/pages/data.py
swarm_squad/pages/footer.py
swarm_squad/pages/home.py
swarm_squad/pages/log.py
swarm_squad/pages/map.py
swarm_squad/pages/nav.py
swarm_squad/pages/plot.py
swarm_squad/scripts/__init__.py
swarm_squad/scripts/boids.py
swarm_squad/scripts/formation.py
swarm_squad/utils/__init__.py
swarm_squad/utils/db_init.py
swarm_squad/utils/db_writer.py
swarm_squad/utils/logger.py
swarm_squad/utils/map_fetcher.py
swarm_squad/utils/websocket_manager.py
swarm_squad/utils/websocket_server.py
swarm_squad/utils/websocket_writer.py
swarm_squad-0.1.8.dist-info/METADATA
swarm_squad-0.1.8.dist-info/WHEEL
swarm_squad-0.1.8.dist-info/entry_points.txt
swarm_squad-0.1.8.dist-info/licenses/LICENSE
swarm_squad-0.1.8.dist-info/RECORD
