Metadata-Version: 2.4
Name: swarm-squad
Version: 0.1.8
Summary: Swarm Squad: A simulation framework for multi-agent systems.
Project-URL: Homepage, https://swarm-squad.com
Project-URL: Documentation, https://docs.swarm-squad.com
Project-URL: Repository, https://github.com/Swarm-Squad/Swarm-Squad
Author-email: Sang Buster <hello@singsongaftermath.com>
License: MIT License
License-File: LICENSE
Requires-Python: >=3.10
Requires-Dist: dash-bootstrap-components>=2.0.0
Requires-Dist: dash-iconify>=0.1.2
Requires-Dist: dash-mantine-components>=1.1.1
Requires-Dist: dash>=3.0.2
Requires-Dist: flask-cors>=5.0.1
Requires-Dist: matplotlib>=3.10.1
Requires-Dist: pandas>=2.2.3
Requires-Dist: pyqt5>=5.15.11
Requires-Dist: python-dotenv>=1.1.0
Requires-Dist: websockets>=15.0.1
